LangToxicScore.py
langtoxicscore-0.1.2.dist-info/WHEEL
langtoxicscore-0.1.2.dist-info/METADATA
langtoxicscore-0.1.2.dist-info/RECORD
