Metadata-Version: 2.1
Name: langtoxicscore
Version: 0.1.2
Summary: GetToxicity(string)
Author: Dmitry Filinov
Author-email: dm.filinov@gmail.com
Requires-Python: >=3.10,<4.0
Classifier: Programming Language :: Python :: 3
Classifier: Programming Language :: Python :: 3.10
